{"version":2,"kind":"Article","sha256":"81fc69cc54c1f500b2dc3254bdac04ad4996018b1172849afeaac75b1cf37d49","slug":"index-93d9baee4b74ec-165a8c9c49a36a791655f8e35cccc","location":"/docs/build/index-93d9baee4b74ec-165a8c9c49a36a791655f8e35cccc838.md","dependencies":[],"frontmatter":{"title":"Mathematics for Economists II","content_includes_title":false,"numbering":{"title":{"offset":2}},"exports":[{"format":"md","filename":"index-93d9baee4b74ec-165a8c9c49a36a791655f8e35cccc838.md","url":"/index-93d9baee4b74ec-fb08c9bd7719cb19ce174508ab796427.md"}]},"mdast":{"type":"root","children":[{"type":"block","children":[{"type":"paragraph","position":{"start":{"line":3,"column":1},"end":{"line":3,"column":1}},"children":[{"type":"text","value":"These notes introduce core mathematical tools used in economics and related fields.","position":{"start":{"line":3,"column":1},"end":{"line":3,"column":1}},"key":"TGIN1xwZd9"}],"key":"iCT3RttDBd"},{"type":"paragraph","position":{"start":{"line":5,"column":1},"end":{"line":6,"column":1}},"children":[{"type":"text","value":"The material is organized by topic and is intended to be intuitive,\nexample-driven, and minimally technical where possible.","position":{"start":{"line":5,"column":1},"end":{"line":5,"column":1}},"key":"bDcNGjG2BT"}],"key":"O9X0CB8dtJ"},{"type":"heading","depth":2,"position":{"start":{"line":8,"column":1},"end":{"line":8,"column":1}},"children":[{"type":"text","value":"Topics","position":{"start":{"line":8,"column":1},"end":{"line":8,"column":1}},"key":"bST83Qxoq4"}],"identifier":"topics","label":"Topics","html_id":"topics","implicit":true,"key":"bbK53TzSlp"},{"type":"list","ordered":false,"spread":false,"position":{"start":{"line":10,"column":1},"end":{"line":13,"column":1}},"children":[{"type":"listItem","spread":true,"position":{"start":{"line":10,"column":1},"end":{"line":10,"column":1}},"children":[{"type":"link","url":"absolute-basics.md","position":{"start":{"line":10,"column":1},"end":{"line":10,"column":1}},"children":[{"type":"text","value":"Absolute Basics","position":{"start":{"line":10,"column":1},"end":{"line":10,"column":1}},"key":"vxMJMxupEh"}],"urlSource":"absolute-basics.md","key":"pxqjDVa79E"}],"key":"QOW3Prrra8"},{"type":"listItem","spread":true,"position":{"start":{"line":11,"column":1},"end":{"line":11,"column":1}},"children":[{"type":"link","url":"linear-algebra-basic.md","position":{"start":{"line":11,"column":1},"end":{"line":11,"column":1}},"children":[{"type":"text","value":"Linear Algebra (Basics)","position":{"start":{"line":11,"column":1},"end":{"line":11,"column":1}},"key":"X1uU6blSIc"}],"urlSource":"linear-algebra-basic.md","key":"SvMLF4WkQE"}],"key":"y9IdFhmDij"},{"type":"listItem","spread":true,"position":{"start":{"line":12,"column":1},"end":{"line":13,"column":1}},"children":[{"type":"link","url":"linear-algebra-special.md","position":{"start":{"line":12,"column":1},"end":{"line":12,"column":1}},"children":[{"type":"text","value":"Linear Algebra (Special Matrices)","position":{"start":{"line":12,"column":1},"end":{"line":12,"column":1}},"key":"kk0AEyVNNz"}],"urlSource":"linear-algebra-special.md","key":"zEOCEfYddA"}],"key":"h8NBiXBou6"}],"key":"Im28bq16yN"},{"type":"paragraph","position":{"start":{"line":14,"column":1},"end":{"line":14,"column":1}},"children":[{"type":"text","value":"More topics will be added:","position":{"start":{"line":14,"column":1},"end":{"line":14,"column":1}},"key":"ESWwkU9c09"}],"key":"Seu6lKzn3o"},{"type":"list","ordered":false,"spread":false,"position":{"start":{"line":15,"column":1},"end":{"line":17,"column":1}},"children":[{"type":"listItem","spread":true,"position":{"start":{"line":15,"column":1},"end":{"line":15,"column":1}},"children":[{"type":"text","value":"Calculus","position":{"start":{"line":15,"column":1},"end":{"line":15,"column":1}},"key":"ZG6uwxXl8c"}],"key":"Ms8LwRnHow"},{"type":"listItem","spread":true,"position":{"start":{"line":16,"column":1},"end":{"line":16,"column":1}},"children":[{"type":"text","value":"Difference equations","position":{"start":{"line":16,"column":1},"end":{"line":16,"column":1}},"key":"KJ9pQZYUrL"}],"key":"IUQmbqODMV"},{"type":"listItem","spread":true,"position":{"start":{"line":17,"column":1},"end":{"line":17,"column":1}},"children":[{"type":"text","value":"Differential equations","position":{"start":{"line":17,"column":1},"end":{"line":17,"column":1}},"key":"KizCRnRzyC"}],"key":"zX2GATCKAy"}],"key":"ixCPBe2xKb"}],"key":"BX2Hcr0YXS"}],"key":"vNFr8wu7xR"},"references":{"cite":{"order":[],"data":{}}}}