{"version":2,"kind":"Article","sha256":"8ab0ee082ddaa9ad0268b40636e56cf45be7797f4459624ae5c2c02d7047eaf9","slug":"index-ceda07ea84cf21-cdf7514401df006633002f4c26b07","location":"/docs/build/index-ceda07ea84cf21-cdf7514401df006633002f4c26b07a36.md","dependencies":[],"frontmatter":{"title":"Mathematics for Economists II","content_includes_title":false,"numbering":{"title":{"offset":2}},"exports":[{"format":"md","filename":"index-ceda07ea84cf21-cdf7514401df006633002f4c26b07a36.md","url":"/index-ceda07ea84cf21-77fdcd4d39c47271f9fd0b05e6a7b410.md"}]},"mdast":{"type":"root","children":[{"type":"block","children":[{"type":"paragraph","position":{"start":{"line":3,"column":1},"end":{"line":3,"column":1}},"children":[{"type":"text","value":"These notes introduce core mathematical tools used in economics and related fields.","position":{"start":{"line":3,"column":1},"end":{"line":3,"column":1}},"key":"zKmtTBfQLw"}],"key":"TmA7ob7yhv"},{"type":"paragraph","position":{"start":{"line":5,"column":1},"end":{"line":5,"column":1}},"children":[{"type":"text","value":"The material is organized by topic and is intended to be intuitive, example-driven, and minimally technical where possible.","position":{"start":{"line":5,"column":1},"end":{"line":5,"column":1}},"key":"LNlIxRvKD5"}],"key":"hm5HhVgEfx"},{"type":"heading","depth":2,"position":{"start":{"line":7,"column":1},"end":{"line":7,"column":1}},"children":[{"type":"text","value":"Topics","position":{"start":{"line":7,"column":1},"end":{"line":7,"column":1}},"key":"LZN5MzApAf"}],"identifier":"topics","label":"Topics","html_id":"topics","implicit":true,"key":"AdscOcgQvo"},{"type":"list","ordered":false,"spread":false,"position":{"start":{"line":9,"column":1},"end":{"line":12,"column":1}},"children":[{"type":"listItem","spread":true,"position":{"start":{"line":9,"column":1},"end":{"line":9,"column":1}},"children":[{"type":"link","url":"absolute-basics.md","position":{"start":{"line":9,"column":1},"end":{"line":9,"column":1}},"children":[{"type":"text","value":"Absolute Basics","position":{"start":{"line":9,"column":1},"end":{"line":9,"column":1}},"key":"zpj8fvPbJD"}],"urlSource":"absolute-basics.md","key":"wqFRpOPFTV"}],"key":"q61yWnjzZi"},{"type":"listItem","spread":true,"position":{"start":{"line":10,"column":1},"end":{"line":10,"column":1}},"children":[{"type":"link","url":"linear-algebra-basic.md","position":{"start":{"line":10,"column":1},"end":{"line":10,"column":1}},"children":[{"type":"text","value":"Linear Algebra (Basics)","position":{"start":{"line":10,"column":1},"end":{"line":10,"column":1}},"key":"PpcXUDU9Ho"}],"urlSource":"linear-algebra-basic.md","key":"ZK12KdEqOq"}],"key":"cFj4jL2QQB"},{"type":"listItem","spread":true,"position":{"start":{"line":11,"column":1},"end":{"line":12,"column":1}},"children":[{"type":"link","url":"linear-algebra-special.md","position":{"start":{"line":11,"column":1},"end":{"line":11,"column":1}},"children":[{"type":"text","value":"Linear Algebra (Special Matrices)","position":{"start":{"line":11,"column":1},"end":{"line":11,"column":1}},"key":"oYimxlXiiQ"}],"urlSource":"linear-algebra-special.md","key":"rXEBgeoUjG"}],"key":"kykd5UuC1l"}],"key":"oRxirMcGe6"},{"type":"paragraph","position":{"start":{"line":13,"column":1},"end":{"line":13,"column":1}},"children":[{"type":"text","value":"More topics will be added:","position":{"start":{"line":13,"column":1},"end":{"line":13,"column":1}},"key":"mLMDtLWhNA"}],"key":"qMhCLmVyjW"},{"type":"list","ordered":false,"spread":false,"position":{"start":{"line":15,"column":1},"end":{"line":20,"column":1}},"children":[{"type":"listItem","spread":true,"position":{"start":{"line":15,"column":1},"end":{"line":15,"column":1}},"children":[{"type":"text","value":"Calculus","position":{"start":{"line":15,"column":1},"end":{"line":15,"column":1}},"key":"o7iJRU354m"}],"key":"fOaZ1ehLFZ"},{"type":"listItem","spread":true,"position":{"start":{"line":16,"column":1},"end":{"line":16,"column":1}},"children":[{"type":"text","value":"Optimization","position":{"start":{"line":16,"column":1},"end":{"line":16,"column":1}},"key":"DmzyNLVpJx"}],"key":"si14eTKyq8"},{"type":"listItem","spread":true,"position":{"start":{"line":17,"column":1},"end":{"line":17,"column":1}},"children":[{"type":"text","value":"Integration","position":{"start":{"line":17,"column":1},"end":{"line":17,"column":1}},"key":"xuJxncsFks"}],"key":"toaTEyzxlS"},{"type":"listItem","spread":true,"position":{"start":{"line":18,"column":1},"end":{"line":18,"column":1}},"children":[{"type":"text","value":"Difference equations","position":{"start":{"line":18,"column":1},"end":{"line":18,"column":1}},"key":"COJkq78wCX"}],"key":"iuHYsQyaNF"},{"type":"listItem","spread":true,"position":{"start":{"line":19,"column":1},"end":{"line":20,"column":1}},"children":[{"type":"text","value":"Differential equations","position":{"start":{"line":19,"column":1},"end":{"line":19,"column":1}},"key":"er315raDLT"}],"key":"kCagAf1aME"}],"key":"BXnYhM7nCE"},{"type":"paragraph","position":{"start":{"line":21,"column":1},"end":{"line":21,"column":1}},"children":[{"type":"text","value":"Notes prepared by -YY- (please do not distribute without permission)","position":{"start":{"line":21,"column":1},"end":{"line":21,"column":1}},"key":"cgCCHnO42v"}],"key":"wPQ7ApzGca"},{"type":"comment","value":" test ","key":"OfoaAXGuom"}],"key":"KyYApdQq73"}],"key":"itpQNZNY59"},"references":{"cite":{"order":[],"data":{}}}}